README.md
setup.py
liveaction/__init__.py
liveaction/liveaction.py
liveaction.egg-info/PKG-INFO
liveaction.egg-info/SOURCES.txt
liveaction.egg-info/dependency_links.txt
liveaction.egg-info/top_level.txt