Metadata-Version: 1.0
Name: liveaction
Version: 0.1.9
Summary: Liveaction API module
Home-page: UNKNOWN
Author: Vecheka Chhourn
Author-email: vecheka.chhourn@nordstrom.com
License: MIT
Keywords: LiveAction,liveaction
Platform: UNKNOWN
